greatjob/__init__.py
greatjob/imageleap
greatjob/sparkle.png
greatjob/thumbsup.png
greatjob/proj/__init__.py
greatjob-1.1.1.dist-info/DESCRIPTION.rst
greatjob-1.1.1.dist-info/entry_points.txt
greatjob-1.1.1.dist-info/METADATA
greatjob-1.1.1.dist-info/metadata.json
greatjob-1.1.1.dist-info/pbr.json
greatjob-1.1.1.dist-info/RECORD
greatjob-1.1.1.dist-info/top_level.txt
greatjob-1.1.1.dist-info/WHEEL
