Metadata-Version: 2.0
Name: greatjob
Version: 1.1.1
Summary: Congratulations
Home-page: UNKNOWN
Author: Celeen Rusk
Author-email: celeenrusk@gmail.com
License: UNKNOWN
Platform: UNKNOWN
